.gitignore
README.rst
setup.py
django-star_demo/src/django_star_demo/__init__.py
django-star_demo/src/django_star_demo/manage.py
django-star_demo/src/django_star_demo/settings.py
django-star_demo/src/django_star_demo/urls.py
django-star_demo/src/django_star_demo/blogs/__init__.py
django-star_demo/src/django_star_demo/blogs/admin.py
django-star_demo/src/django_star_demo/blogs/models.py
django-star_demo/src/django_star_demo/blogs/tests.py
django-star_demo/src/django_star_demo/blogs/urls.py
django-star_demo/src/django_star_demo/blogs/views.py
django-star_demo/src/django_star_demo/blogs/fixtures/initial_data.json
django-star_demo/static/js/jquery-1.6.4.min.js
django-star_demo/templates/base.html
django-star_demo/templates/index.html
django-star_demo/templates/blogs/entry_detail.html
django_star.egg-info/PKG-INFO
django_star.egg-info/SOURCES.txt
django_star.egg-info/dependency_links.txt
django_star.egg-info/top_level.txt
star/__init__.py
star/admin.py
star/models.py
star/tests.py
star/api/__init__.py
star/api/handlers.py
star/api/urls.py
star/locale/ja/LC_MESSAGES/django.po
star/static/css/django.star.css
star/static/css/django-star-img/plus-circle-frame.png
star/static/css/django-star-img/plus-circle.png
star/static/css/django-star-img/star.png
star/static/js/django.star.js
star/static/js/django.star.min.js
star/templates/star/head.html
star/templates/star/list.html
star/templatetags/__init__.py
star/templatetags/djangostar.py
util/setup.sh