Metadata-Version: 1.0
Name: django-star
Version: 0.999
Summary: Django plugin for adding a star to Django model object universally.
Home-page: https://github.com/giginet/django-star
Author: giginet
Author-email: giginet.net@gmail.com
License: BSD
Download-URL: https://github.com/giginet/django-star/tarball/master
Keywords: django hatena star
Platform: UNKNOWN
Classifier: Intended Audience :: Developers
Classifier: License :: OSI Approved :: BSD License
Classifier: Programming Language :: Python
Classifier: Topic :: Internet :: WWW/HTTP
